[
    {
        "word": "alma",
        "timestamp": 1618657292858
    },
    {
        "word": "csirke",
        "timestamp": 1620126108295
    },
    {
        "word": "joghurt",
        "timestamp": 1620730896162
    },
    {
        "word": "virsli",
        "timestamp": 1412226590867
    },
    {
        "word": "párizsi",
        "timestamp": 1412225197128
    },
    {
        "word": "Pick",
        "timestamp": 1616842858029
    },
    {
        "word": "kávé",
        "timestamp": 1620471647825
    },
    {
        "word": "sajt",
        "timestamp": 1621076481800
    }
]